secret_store/__init__.py
secret_store/_version.py
secret_store/secret_store.py
secret_store/secret_store_cli.py
secret_store/stores/__init__.py
secret_store/stores/aws_store.py
secret_store/stores/azure_store.py
secret_store/stores/local_store.py
secret_store_gor-1.0.4.dist-info/licenses/LICENSE
secret_store_gor-1.0.4.dist-info/METADATA
secret_store_gor-1.0.4.dist-info/WHEEL
secret_store_gor-1.0.4.dist-info/top_level.txt
secret_store_gor-1.0.4.dist-info/RECORD
